{
  "project_info": {
    "project_number": "1049198394355",
    "project_id": "officeproject-b7ab4",
    "storage_bucket": "officeproject-b7ab4.appspot.com"
  },
  "client": [
    {
      "client_info": {
        "mobilesdk_app_id": "1:1049198394355:android:540f50cbeb40a95bf57086",
        "android_client_info": {
          "package_name": "com.example.officeproject"
        }
      },
      "oauth_client": [
        {
          "client_id": "1049198394355-lm2lvn5o65g5chf6q3bbthr2t34hts97.apps.googleusercontent.com",
          "client_type": 3
        }
      ],
      "api_key": [
        {
          "current_key": "AIzaSyA1U5YGag8I2x_8XnoRID2U0impXVW7EEw"
        }
      ],
      "services": {
        "appinvite_service": {
          "other_platform_oauth_client": [
            {
              "client_id": "1049198394355-lm2lvn5o65g5chf6q3bbthr2t34hts97.apps.googleusercontent.com",
              "client_type": 3
            }
          ]
        }
      }
    }
  ],
  "configuration_version": "1"
}